README
setup.py
xmlrpcdo.py
xmlrpcdo.egg-info/PKG-INFO
xmlrpcdo.egg-info/SOURCES.txt
xmlrpcdo.egg-info/dependency_links.txt
xmlrpcdo.egg-info/entry_points.txt
xmlrpcdo.egg-info/top_level.txt