Metadata-Version: 1.0
Name: xmlrpcdo
Version: 0.1.post1
Summary: XML-RPC request fiddler
Home-page: https://bitbucket.org/michaelgruenewald/xmlrpcdo
Author: Michael Gruenewald
Author-email: mail@michaelgruenewald.eu
License: License :: OSI Approved :: GPL License
Platform: UNKNOWN
